exc/__init__.py
exc/bit.py
exc/boyorgirl.py
exc/playoff.py
exc/toolongstrings.py
pygadgets/__init__.py
pygadgets/__main__.py
pygadgets/ceidg.py
pygadgets/svc.py
pygadgets/util.py
tests/__init__.py
tests/conftest.py
tests/test_config.py
tests/test_exc.py
tests/test_svc.py
tests/test_unit_ceidg.py
pygadgets-0.1.2.dist-info/LICENSE
pygadgets-0.1.2.dist-info/METADATA
pygadgets-0.1.2.dist-info/WHEEL
pygadgets-0.1.2.dist-info/top_level.txt
pygadgets-0.1.2.dist-info/RECORD
