Metadata-Version: 2.1
Name: pygadgets
Version: 0.1.2
Summary: programming resources and utils
Home-page: UNKNOWN
Author: pnowk
Author-email: pnowk123@gmail.com
License: MIT
Keywords: python
Platform: UNKNOWN
Classifier: Development Status :: 3 - Alpha
Classifier: Intended Audience :: Developers
Classifier: License :: OSI Approved :: MIT License
Classifier: Programming Language :: Python :: 3
Requires-Dist: twine
Requires-Dist: python-dotenv
Requires-Dist: wheel
Requires-Dist: black
Requires-Dist: bumpversion
Requires-Dist: pytest
